freeact_skills/__init__.py
freeact_skills/editor/README.md
freeact_skills/editor/__init__.py
freeact_skills/editor/impl.py
freeact_skills/editor/run.py
freeact_skills/reader/__init__.py
freeact_skills/reader/api.py
freeact_skills/reader/impl.py
freeact_skills/resume/__init__.py
freeact_skills/resume/citations.py
freeact_skills/resume/resume.py
freeact_skills/resume/resume.yaml
freeact_skills/search/google/__init__.py
freeact_skills/search/google/api.py
freeact_skills/search/google/impl.py
freeact_skills/search/google/stream/__init__.py
freeact_skills/search/google/stream/api.py
freeact_skills/search/perplexity/__init__.py
freeact_skills/search/perplexity/api.py
freeact_skills/search/perplexity/impl.py
freeact_skills/zotero/__init__.py
freeact_skills/zotero/api.py
freeact_skills/zotero/impl.py
freeact_skills-0.0.8.dist-info/LICENSE
freeact_skills-0.0.8.dist-info/METADATA
freeact_skills-0.0.8.dist-info/WHEEL
freeact_skills-0.0.8.dist-info/RECORD
